datarobot_batch_scoring/__init__.py
datarobot_batch_scoring/batch_scoring.py
datarobot_batch_scoring/consts.py
datarobot_batch_scoring/detect.py
datarobot_batch_scoring/exceptions.py
datarobot_batch_scoring/main.py
datarobot_batch_scoring/reader.py
datarobot_batch_scoring/utils.py
datarobot_batch_scoring/writer.py
datarobot_batch_scoring/api_response_handlers/__init__.py
datarobot_batch_scoring/api_response_handlers/api_v1.py
datarobot_batch_scoring/api_response_handlers/pred_api_v10.py
datarobot_batch_scoring/network/__init__.py
datarobot_batch_scoring/network/base_network_worker.py
datarobot_batch_scoring/network/dry_run.py
datarobot_batch_scoring/network/network.py
datarobot_batch_scoring-1.16.5.dist-info/LICENSE.txt
datarobot_batch_scoring-1.16.5.dist-info/METADATA
datarobot_batch_scoring-1.16.5.dist-info/WHEEL
datarobot_batch_scoring-1.16.5.dist-info/entry_points.txt
datarobot_batch_scoring-1.16.5.dist-info/top_level.txt
datarobot_batch_scoring-1.16.5.dist-info/RECORD
