Metadata-Version: 2.1
Name: datarobot-batch-scoring
Version: 1.16.5
Summary: A script to score CSV files via DataRobot's prediction API
Home-page: http://www.datarobot.com/
Author: DataRobot
Author-email: support@datarobot.com
Maintainer: DataRobot
Maintainer-email: support@datarobot.com
License: BSD
Platform: UNKNOWN
Classifier: License :: OSI Approved :: Apache Software License
Classifier: Programming Language :: Python :: 2.7
Classifier: Programming Language :: Python :: 3.4
Classifier: Programming Language :: Python :: 3.5
Requires-Dist: six (>=1.9.0)
Requires-Dist: requests (>=2.20.0)
Requires-Dist: trafaret (!=1.1.0,<2.0,>=0.9)
Requires-Dist: contextlib2 (>=0.5.1)
Requires-Dist: chardet (>=3.0.2<3.1.0)
Requires-Dist: futures (>=3.0.4)
